loadupch/__init__.py
loadupch/__main__.py
loadupch/app.py
loadupch-0.0.3.dist-info/LICENSE
loadupch-0.0.3.dist-info/METADATA
loadupch-0.0.3.dist-info/WHEEL
loadupch-0.0.3.dist-info/top_level.txt
loadupch-0.0.3.dist-info/RECORD
