Metadata-Version: 2.1
Name: loadupch
Version: 0.0.3
Summary: Uploader tool for flashing firmware onto the CH552 device. v0.0.3 win&lin
Author: Master
Author-email: name@email.com
License: GPL-3.0 License
License-File: LICENSE
Requires-Dist: tk
Requires-Dist: pyusb
